{"197907": {"files": {"oa_pdf/a7/bf/jc821239.PMC2110407.pdf": {"url_count": 0, "annot_urls": [], "text_urls": [], "all_urls": []}, "oa_pdf/e5/51/jc821174.PMC2110408.pdf": {"url_count": 0, "annot_urls": [], "text_urls": [], "all_urls": []}, "oa_pdf/d6/8d/jc821227.PMC2110409.pdf": {"url_count": 0, "annot_urls": [], "text_urls": [], "all_urls": []}, "oa_pdf/0d/65/jc82193.PMC2110410.pdf": {"url_count": 0, "annot_urls": [], "text_urls": [], "all_urls": []}, "oa_pdf/31/5d/jc821264.PMC2110411.pdf": {"url_count": 0, "annot_urls": [], "text_urls": [], "all_urls": []}, "oa_pdf/c0/ef/jc821150.PMC2110412.pdf": {"url_count": 0, "annot_urls": [], "text_urls": [], "all_urls": []}, "oa_pdf/3b/08/86.PMC2110413.pdf": {"url_count": 0, "annot_urls": [], "text_urls": [], "all_urls": []}, "oa_pdf/fe/0b/jc821195.PMC2110414.pdf": {"url_count": 0, "annot_urls": [], "text_urls": [], "all_urls": []}, "oa_pdf/b7/64/jc82117.PMC2110415.pdf": {"url_count": 0, "annot_urls": [], "text_urls": [], "all_urls": []}, "oa_pdf/01/86/jc82157.PMC2110416.pdf": {"url_count": 0, "annot_urls": [], "text_urls": [], "all_urls": []}, "oa_pdf/36/fb/jc821185.PMC2110417.pdf": {"url_count": 0, "annot_urls": [], "text_urls": [], "all_urls": []}, "oa_pdf/1c/3c/jc821212.PMC2110418.pdf": {"url_count": 0, "annot_urls": [], "text_urls": [], "all_urls": []}, "oa_pdf/26/10/jc82145.PMC2110419.pdf": {"url_count": 0, "annot_urls": [], "text_urls": [], "all_urls": []}, "oa_pdf/b4/82/291.PMC2110420.pdf": {"url_count": 0, "annot_urls": [], "text_urls": [], "all_urls": []}, "oa_pdf/d0/84/jc821278.PMC2110421.pdf": {"url_count": 0, "annot_urls": [], "text_urls": [], "all_urls": []}, "oa_pdf/e8/50/jc821248.PMC2110422.pdf": {"url_count": 0, "annot_urls": [], "text_urls": [], "all_urls": []}, "oa_pdf/4c/8b/jc821114.PMC2110423.pdf": {"url_count": 0, "annot_urls": [], "text_urls": [], "all_urls": []}, "oa_pdf/d0/62/jc82176.PMC2110424.pdf": {"url_count": 0, "annot_urls": [], "text_urls": [], "all_urls": []}, "oa_pdf/3d/9c/jc821140.PMC2110425.pdf": {"url_count": 0, "annot_urls": [], "text_urls": [], "all_urls": []}, "oa_pdf/42/93/jc82166.PMC2110426.pdf": {"url_count": 0, "annot_urls": [], "text_urls": [], "all_urls": []}, "oa_pdf/12/54/jc821299.PMC2110427.pdf": {"url_count": 0, "annot_urls": [], "text_urls": [], "all_urls": []}, "oa_pdf/42/b9/jc821103.PMC2110428.pdf": {"url_count": 0, "annot_urls": [], "text_urls": [], "all_urls": []}, "oa_pdf/89/2c/jc8211.PMC2110429.pdf": {"url_count": 0, "annot_urls": [], "text_urls": [], "all_urls": []}, "oa_pdf/d0/ce/jc82132.PMC2110430.pdf": {"url_count": 0, "annot_urls": [], "text_urls": [], "all_urls": []}, "oa_pdf/4d/fa/je150186.PMC2185600.pdf": {"url_count": 0, "annot_urls": [], "text_urls": [], "all_urls": []}, "oa_pdf/12/5b/je1501166.PMC2185601.pdf": {"url_count": 0, "annot_urls": [], "text_urls": [], "all_urls": []}, "oa_pdf/87/93/je150110.PMC2185602.pdf": {"url_count": 0, "annot_urls": [], "text_urls": [], "all_urls": []}, "oa_pdf/9a/99/je150131.PMC2185603.pdf": {"url_count": 0, "annot_urls": [], "text_urls": [], "all_urls": []}, "oa_pdf/57/59/je150144.PMC2185604.pdf": {"url_count": 0, "annot_urls": [], "text_urls": [], "all_urls": []}, "oa_pdf/4d/fc/je1501108.PMC2185605.pdf": {"url_count": 0, "annot_urls": [], "text_urls": [], "all_urls": []}, "oa_pdf/13/cd/20.PMC2185606.pdf": {"url_count": 0, "annot_urls": [], "text_urls": [], "all_urls": []}, "oa_pdf/f2/c9/je1501127.PMC2185607.pdf": {"url_count": 0, "annot_urls": [], "text_urls": [], "all_urls": []}, "oa_pdf/c6/58/138.PMC2185608.pdf": {"url_count": 0, "annot_urls": [], "text_urls": [], "all_urls": []}, "oa_pdf/3c/6f/je1501184.PMC2185609.pdf": {"url_count": 0, "annot_urls": [], "text_urls": [], "all_urls": []}, "oa_pdf/e6/77/je1501196.PMC2185610.pdf": {"url_count": 0, "annot_urls": [], "text_urls": [], "all_urls": []}, "oa_pdf/f9/4e/174.PMC2185611.pdf": {"url_count": 0, "annot_urls": [], "text_urls": [], "all_urls": []}, "oa_pdf/03/0e/51.PMC2185612.pdf": {"url_count": 0, "annot_urls": [], "text_urls": [], "all_urls": []}, "oa_pdf/31/d0/je1501117.PMC2185613.pdf": {"url_count": 0, "annot_urls": [], "text_urls": [], "all_urls": []}, "oa_pdf/a7/f5/je15011.PMC2185614.pdf": {"url_count": 0, "annot_urls": [], "text_urls": [], "all_urls": []}, "oa_pdf/e7/36/154.PMC2185615.pdf": {"url_count": 0, "annot_urls": [], "text_urls": [], "all_urls": []}, "oa_pdf/fb/be/je1501100.PMC2185616.pdf": {"url_count": 0, "annot_urls": [], "text_urls": [], "all_urls": []}, "oa_pdf/27/a4/67.PMC2185617.pdf": {"url_count": 0, "annot_urls": [], "text_urls": [], "all_urls": []}, "oa_pdf/71/39/jg74137.PMC2228479.pdf": {"url_count": 0, "annot_urls": [], "text_urls": [], "all_urls": []}, "oa_pdf/41/f7/jg74117.PMC2228480.pdf": {"url_count": 0, "annot_urls": [], "text_urls": [], "all_urls": []}, "oa_pdf/f0/f3/jg74157.PMC2228481.pdf": {"url_count": 0, "annot_urls": [], "text_urls": [], "all_urls": []}, "oa_pdf/29/ec/jg74171.PMC2228482.pdf": {"url_count": 0, "annot_urls": [], "text_urls": [], "all_urls": []}, "oa_pdf/71/13/jg741129.PMC2228483.pdf": {"url_count": 0, "annot_urls": [], "text_urls": [], "all_urls": []}, "oa_pdf/d4/30/jg741105.PMC2228484.pdf": {"url_count": 0, "annot_urls": [], "text_urls": [], "all_urls": []}, "oa_pdf/ff/d2/jg7411.PMC2228485.pdf": {"url_count": 0, "annot_urls": [], "text_urls": [], "all_urls": []}, "oa_pdf/ca/63/jg74185.PMC2228486.pdf": {"url_count": 0, "annot_urls": [], "text_urls": [], "all_urls": []}, "oa_pdf/dc/90/indmedgaz70722-0025a.PMC5146357.pdf": {"url_count": 0, "annot_urls": [], "text_urls": [], "all_urls": []}, "oa_pdf/c4/e7/indmedgaz70722-0020.PMC5146358.pdf": {"url_count": 0, "annot_urls": [], "text_urls": [], "all_urls": []}, "oa_pdf/d0/d6/indmedgaz70722-0013.PMC5146359.pdf": {"url_count": 0, "annot_urls": [], "text_urls": [], "all_urls": []}, "oa_pdf/97/5c/indmedgaz70722-0024c.PMC5146360.pdf": {"url_count": 0, "annot_urls": [], "text_urls": [], "all_urls": []}, "oa_pdf/3a/9f/indmedgaz70722-0017b.PMC5146361.pdf": {"url_count": 0, "annot_urls": [], "text_urls": [], "all_urls": []}, "oa_pdf/7f/bc/indmedgaz70722-0026a.PMC5146362.pdf": {"url_count": 0, "annot_urls": [], "text_urls": [], "all_urls": []}, "oa_pdf/55/e3/indmedgaz70722-0022.PMC5146363.pdf": {"url_count": 0, "annot_urls": [], "text_urls": [], "all_urls": []}, "oa_pdf/8d/b8/indmedgaz70722-0017a.PMC5146365.pdf": {"url_count": 0, "annot_urls": [], "text_urls": [], "all_urls": []}, "oa_pdf/5e/62/indmedgaz70722-0029.PMC5146366.pdf": {"url_count": 0, "annot_urls": [], "text_urls": [], "all_urls": []}, "oa_pdf/82/95/indmedgaz70722-0028.PMC5146369.pdf": {"url_count": 0, "annot_urls": [], "text_urls": [], "all_urls": []}, "oa_pdf/37/99/indmedgaz70722-0011.PMC5146371.pdf": {"url_count": 0, "annot_urls": [], "text_urls": [], "all_urls": []}, "oa_pdf/dd/9e/indmedgaz70722-0025b.PMC5146373.pdf": {"url_count": 0, "annot_urls": [], "text_urls": [], "all_urls": []}, "oa_pdf/82/d9/indmedgaz70722-0012.PMC5146374.pdf": {"url_count": 0, "annot_urls": [], "text_urls": [], "all_urls": []}, "oa_pdf/48/f9/indmedgaz70722-0024a.PMC5146375.pdf": {"url_count": 0, "annot_urls": [], "text_urls": [], "all_urls": []}, "oa_pdf/63/70/indmedgaz70722-0018.PMC5146376.pdf": {"url_count": 0, "annot_urls": [], "text_urls": [], "all_urls": []}, "oa_pdf/ac/60/indmedgaz70722-0026b.PMC5146377.pdf": {"url_count": 0, "annot_urls": [], "text_urls": [], "all_urls": []}, "oa_pdf/92/8b/indmedgaz70722-0025c.PMC5146378.pdf": {"url_count": 0, "annot_urls": [], "text_urls": [], "all_urls": []}, "oa_pdf/79/8b/indmedgaz70722-0001.PMC5146379.pdf": {"url_count": 0, "annot_urls": [], "text_urls": [], "all_urls": []}, "oa_pdf/56/d3/indmedgaz70722-0017c.PMC5146380.pdf": {"url_count": 0, "annot_urls": [], "text_urls": [], "all_urls": []}, "oa_pdf/9c/85/indmedgaz70722-0008.PMC5146383.pdf": {"url_count": 0, "annot_urls": [], "text_urls": [], "all_urls": []}, "oa_pdf/96/e0/indmedgaz70722-0024b.PMC5146384.pdf": {"url_count": 0, "annot_urls": [], "text_urls": [], "all_urls": []}, "oa_pdf/c8/1c/edinbmedj74064-0098.PMC5317904.pdf": {"url_count": 0, "annot_urls": [], "text_urls": [], "all_urls": []}, "oa_pdf/d3/26/edinbmedj74064-0064a.PMC5317905.pdf": {"url_count": 0, "annot_urls": [], "text_urls": [], "all_urls": []}, "oa_pdf/cf/ae/edinbmedj74064-0096b.PMC5317906.pdf": {"url_count": 0, "annot_urls": [], "text_urls": [], "all_urls": []}, "oa_pdf/ab/b0/edinbmedj74064-0083.PMC5317907.pdf": {"url_count": 0, "annot_urls": [], "text_urls": [], "all_urls": []}, "oa_pdf/c2/cc/edinbmedj74064-0094.PMC5317908.pdf": {"url_count": 0, "annot_urls": [], "text_urls": [], "all_urls": []}, "oa_pdf/a6/2e/edinbmedj74064-0101b.PMC5317910.pdf": {"url_count": 0, "annot_urls": [], "text_urls": [], "all_urls": []}, "oa_pdf/de/76/edinbmedj74064-0067b.PMC5317911.pdf": {"url_count": 0, "annot_urls": [], "text_urls": [], "all_urls": []}, "oa_pdf/0a/c6/edinbmedj74064-0068.PMC5317913.pdf": {"url_count": 0, "annot_urls": [], "text_urls": [], "all_urls": []}, "oa_pdf/56/68/edinbmedj74064-0096a.PMC5317914.pdf": {"url_count": 0, "annot_urls": [], "text_urls": [], "all_urls": []}, "oa_pdf/54/83/edinbmedj74064-0074.PMC5317915.pdf": {"url_count": 0, "annot_urls": [], "text_urls": [], "all_urls": []}, "oa_pdf/fe/6a/edinbmedj74064-0090.PMC5317916.pdf": {"url_count": 0, "annot_urls": [], "text_urls": [], "all_urls": []}, "oa_pdf/10/f8/edinbmedj74064-0067a.PMC5317917.pdf": {"url_count": 0, "annot_urls": [], "text_urls": [], "all_urls": []}, "oa_pdf/c7/38/edinbmedj74064-0005.PMC5317918.pdf": {"url_count": 0, "annot_urls": [], "text_urls": [], "all_urls": []}, "oa_pdf/ca/f0/edinbmedj74064-0072.PMC5317919.pdf": {"url_count": 0, "annot_urls": [], "text_urls": [], "all_urls": []}, "oa_pdf/9f/13/edinbmedj74064-0101a.PMC5317920.pdf": {"url_count": 0, "annot_urls": [], "text_urls": [], "all_urls": []}, "oa_pdf/ad/4f/edinbmedj74064-0064b.PMC5317921.pdf": {"url_count": 0, "annot_urls": [], "text_urls": [], "all_urls": []}, "oa_pdf/42/5a/edinbmedj74064-0097a.PMC5317922.pdf": {"url_count": 0, "annot_urls": [], "text_urls": [], "all_urls": []}, "oa_pdf/ef/8d/edinbmedj74064-0070.PMC5317923.pdf": {"url_count": 0, "annot_urls": [], "text_urls": [], "all_urls": []}, "oa_pdf/e0/74/edinbmedj74064-0051.PMC5317924.pdf": {"url_count": 0, "annot_urls": [], "text_urls": [], "all_urls": []}, "oa_pdf/1b/c0/edinbmedj74064-0073.PMC5317925.pdf": {"url_count": 0, "annot_urls": [], "text_urls": [], "all_urls": []}, "oa_pdf/5e/81/edinbmedj74064-0101c.PMC5317926.pdf": {"url_count": 0, "annot_urls": [], "text_urls": [], "all_urls": []}, "oa_pdf/be/32/edinbmedj74064-0030.PMC5317927.pdf": {"url_count": 0, "annot_urls": [], "text_urls": [], "all_urls": []}, "oa_pdf/20/7f/edinbmedj74064-0036.PMC5317928.pdf": {"url_count": 0, "annot_urls": [], "text_urls": [], "all_urls": []}, "oa_pdf/8e/84/edinbmedj74064-0085.PMC5317929.pdf": {"url_count": 0, "annot_urls": [], "text_urls": [], "all_urls": []}, "oa_pdf/4d/c1/edinbmedj74064-0044.PMC5317931.pdf": {"url_count": 0, "annot_urls": [], "text_urls": [], "all_urls": []}, "oa_pdf/8b/e7/edinbmedj74064-0100.PMC5317932.pdf": {"url_count": 0, "annot_urls": [], "text_urls": [], "all_urls": []}, "oa_pdf/35/69/edinbmedj74064-0049.PMC5317933.pdf": {"url_count": 0, "annot_urls": [], "text_urls": [], "all_urls": []}, "oa_pdf/d2/ac/edinbmedj74064-0097b.PMC5317934.pdf": {"url_count": 0, "annot_urls": [], "text_urls": [], "all_urls": []}, "oa_pdf/50/22/edinbmedj74064-0025.PMC5317935.pdf": {"url_count": 0, "annot_urls": [], "text_urls": [], "all_urls": []}, "oa_pdf/12/a9/edinbmedj74064-0102.PMC5317936.pdf": {"url_count": 0, "annot_urls": [], "text_urls": [], "all_urls": []}, "oa_pdf/79/f4/edinbmedj74064-0066.PMC5317938.pdf": {"url_count": 0, "annot_urls": [], "text_urls": [], "all_urls": []}, "oa_pdf/a2/12/jrcollphyslond90305-0025.PMC5373185.pdf": {"url_count": 0, "annot_urls": [], "text_urls": [], "all_urls": []}, "oa_pdf/a9/62/jrcollphyslond90305-0029.PMC5373186.pdf": {"url_count": 0, "annot_urls": [], "text_urls": [], "all_urls": []}, "oa_pdf/a6/e5/jrcollphyslond90305-0032.PMC5373187.pdf": {"url_count": 0, "annot_urls": [], "text_urls": [], "all_urls": []}, "oa_pdf/0b/51/jrcollphyslond90305-0005.PMC5373188.pdf": {"url_count": 0, "annot_urls": [], "text_urls": [], "all_urls": []}, "oa_pdf/98/b8/jrcollphyslond90305-0009.PMC5373190.pdf": {"url_count": 0, "annot_urls": [], "text_urls": [], "all_urls": []}, "oa_pdf/88/1f/jrcollphyslond90305-0051.PMC5373191.pdf": {"url_count": 0, "annot_urls": [], "text_urls": [], "all_urls": []}, "oa_pdf/32/35/jrcollphyslond90305-0044.PMC5373192.pdf": {"url_count": 0, "annot_urls": [], "text_urls": [], "all_urls": []}, "oa_pdf/c3/eb/jrcollphyslond90305-0007.PMC5373193.pdf": {"url_count": 0, "annot_urls": [], "text_urls": [], "all_urls": []}, "oa_pdf/5e/45/jrcollphyslond90305-0024.PMC5373194.pdf": {"url_count": 0, "annot_urls": [], "text_urls": [], "all_urls": []}, "oa_pdf/e7/dc/jrcollphyslond90305-0060.PMC5373196.pdf": {"url_count": 0, "annot_urls": [], "text_urls": [], "all_urls": []}, "oa_pdf/bc/51/jrcollphyslond90305-0018.PMC5373197.pdf": {"url_count": 0, "annot_urls": [], "text_urls": [], "all_urls": []}, "oa_pdf/90/75/jrcollphyslond90305-0040.PMC5373198.pdf": {"url_count": 0, "annot_urls": [], "text_urls": [], "all_urls": []}, "oa_pdf/64/8c/jrcollphyslond90305-0058.PMC5373200.pdf": {"url_count": 0, "annot_urls": [], "text_urls": [], "all_urls": []}, "oa_pdf/76/31/glasgowmedj75683-0020.PMC5892464.pdf": {"url_count": 0, "annot_urls": [], "text_urls": [], "all_urls": []}, "oa_pdf/06/af/glasgowmedj75683-0013.PMC5892465.pdf": {"url_count": 0, "annot_urls": [], "text_urls": [], "all_urls": []}, "oa_pdf/c6/65/glasgowmedj75683-0032.PMC5892468.pdf": {"url_count": 0, "annot_urls": [], "text_urls": [], "all_urls": []}, "oa_pdf/20/fe/glasgowmedj75683-0075.PMC5892469.pdf": {"url_count": 0, "annot_urls": [], "text_urls": [], "all_urls": []}, "oa_pdf/ff/de/glasgowmedj75683-0065.PMC5892470.pdf": {"url_count": 0, "annot_urls": [], "text_urls": [], "all_urls": []}, "oa_pdf/f4/8a/glasgowmedj75683-0046.PMC5892472.pdf": {"url_count": 0, "annot_urls": [], "text_urls": [], "all_urls": []}, "oa_pdf/4a/4a/glasgowmedj75683-0071.PMC5892473.pdf": {"url_count": 0, "annot_urls": [], "text_urls": [], "all_urls": []}, "oa_pdf/82/98/glasgowmedj75683-0008.PMC5892474.pdf": {"url_count": 0, "annot_urls": [], "text_urls": [], "all_urls": []}, "oa_pdf/44/8b/glasgowmedj75683-0052.PMC5892475.pdf": {"url_count": 0, "annot_urls": [], "text_urls": [], "all_urls": []}, "oa_pdf/22/2f/glasgowmedj75683-0004.PMC5892476.pdf": {"url_count": 0, "annot_urls": [], "text_urls": [], "all_urls": []}, "oa_pdf/ee/ca/glasgowmedj75683-0030.PMC5892477.pdf": {"url_count": 0, "annot_urls": [], "text_urls": [], "all_urls": []}, "oa_pdf/c9/82/glasgowmedj75683-0042.PMC5892478.pdf": {"url_count": 0, "annot_urls": [], "text_urls": [], "all_urls": []}, "oa_pdf/69/c8/glasgowmedj75683-0034.PMC5892479.pdf": {"url_count": 0, "annot_urls": [], "text_urls": [], "all_urls": []}, "oa_pdf/07/e2/glasgowmedj75683-0040.PMC5892480.pdf": {"url_count": 0, "annot_urls": [], "text_urls": [], "all_urls": []}, "oa_pdf/34/78/glasgowmedj75683-0054.PMC5892481.pdf": {"url_count": 0, "annot_urls": [], "text_urls": [], "all_urls": []}, "oa_pdf/8a/c0/glasgowmedj75683-0038.PMC5892482.pdf": {"url_count": 0, "annot_urls": [], "text_urls": [], "all_urls": []}, "oa_pdf/de/59/glasgowmedj75683-0035.PMC5892483.pdf": {"url_count": 0, "annot_urls": [], "text_urls": [], "all_urls": []}}, "num_files": 290}}