{"199803": {"files": {"oa_pdf/64/cd/245.PMC2117967.pdf": {"url_count": 0, "annot_urls": [], "text_urls": [], "all_urls": []}, "oa_pdf/60/14/147.PMC2117968.pdf": {"url_count": 0, "annot_urls": [], "text_urls": [], "all_urls": []}, "oa_pdf/44/17/29387.PMC2132659.pdf": {"url_count": 1, "annot_urls": [], "text_urls": ["https://www.jcb.org"], "all_urls": ["https://www.jcb.org"]}, "oa_pdf/80/b5/15130.PMC2132660.pdf": {"url_count": 1, "annot_urls": [], "text_urls": ["https://www.jcb.org"], "all_urls": ["https://www.jcb.org"]}, "oa_pdf/1d/52/15157.PMC2132661.pdf": {"url_count": 1, "annot_urls": [], "text_urls": ["https://www.jcb.org"], "all_urls": ["https://www.jcb.org"]}, "oa_pdf/b9/cf/15024.PMC2132662.pdf": {"url_count": 1, "annot_urls": [], "text_urls": ["https://www.jcb.org"], "all_urls": ["https://www.jcb.org"]}, "oa_pdf/8c/c7/29134.PMC2132663.pdf": {"url_count": 1, "annot_urls": [], "text_urls": ["https://www.jcb.org"], "all_urls": ["https://www.jcb.org"]}, "oa_pdf/63/b3/32990.PMC2132664.pdf": {"url_count": 1, "annot_urls": [], "text_urls": ["https://www.jcb.org"], "all_urls": ["https://www.jcb.org"]}, "oa_pdf/e6/17/14666.PMC2132665.pdf": {"url_count": 1, "annot_urls": [], "text_urls": ["https://www.jcb.org"], "all_urls": ["https://www.jcb.org"]}, "oa_pdf/39/9c/9802115.PMC2132666.pdf": {"url_count": 1, "annot_urls": [], "text_urls": ["https://www.jcb.org"], "all_urls": ["https://www.jcb.org"]}, "oa_pdf/fd/d0/10767.PMC2132667.pdf": {"url_count": 1, "annot_urls": [], "text_urls": ["https://www.jcb.org"], "all_urls": ["https://www.jcb.org"]}, "oa_pdf/4f/8f/32976.PMC2132668.pdf": {"url_count": 1, "annot_urls": [], "text_urls": ["https://www.jcb.org"], "all_urls": ["https://www.jcb.org"]}, "oa_pdf/83/0b/29287.PMC2132669.pdf": {"url_count": 1, "annot_urls": [], "text_urls": ["https://www.jcb.org"], "all_urls": ["https://www.jcb.org"]}, "oa_pdf/76/14/12532.PMC2132670.pdf": {"url_count": 1, "annot_urls": [], "text_urls": ["https://www.jcb.org"], "all_urls": ["https://www.jcb.org"]}, "oa_pdf/9f/a6/15111.PMC2132671.pdf": {"url_count": 1, "annot_urls": [], "text_urls": ["https://www.jcb.org"], "all_urls": ["https://www.jcb.org"]}, "oa_pdf/bb/fc/32977.PMC2132672.pdf": {"url_count": 1, "annot_urls": [], "text_urls": ["https://www.jcb.org"], "all_urls": ["https://www.jcb.org"]}, "oa_pdf/74/94/15059.PMC2132673.pdf": {"url_count": 1, "annot_urls": [], "text_urls": ["https://www.jcb.org"], "all_urls": ["https://www.jcb.org"]}, "oa_pdf/ce/7f/32983.PMC2132675.pdf": {"url_count": 1, "annot_urls": [], "text_urls": ["https://www.jcb.org"], "all_urls": ["https://www.jcb.org"]}, "oa_pdf/03/6f/29451.PMC2132676.pdf": {"url_count": 1, "annot_urls": [], "text_urls": ["https://www.jcb.org"], "all_urls": ["https://www.jcb.org"]}, "oa_pdf/46/1f/14720.PMC2132677.pdf": {"url_count": 1, "annot_urls": [], "text_urls": ["https://www.jcb.org"], "all_urls": ["https://www.jcb.org"]}, "oa_pdf/30/b5/29440.PMC2132678.pdf": {"url_count": 1, "annot_urls": [], "text_urls": ["https://www.jcb.org"], "all_urls": ["https://www.jcb.org"]}, "oa_pdf/ce/ea/12568.PMC2132679.pdf": {"url_count": 1, "annot_urls": [], "text_urls": ["https://www.jcb.org"], "all_urls": ["https://www.jcb.org"]}, "oa_pdf/be/56/15104.PMC2132680.pdf": {"url_count": 1, "annot_urls": [], "text_urls": ["https://www.jcb.org"], "all_urls": ["https://www.jcb.org"]}, "oa_pdf/22/32/15125.PMC2132681.pdf": {"url_count": 1, "annot_urls": [], "text_urls": ["https://www.jcb.org"], "all_urls": ["https://www.jcb.org"]}, "oa_pdf/26/c7/16524.PMC2132682.pdf": {"url_count": 1, "annot_urls": [], "text_urls": ["https://www.jcb.org"], "all_urls": ["https://www.jcb.org"]}, "oa_pdf/a3/10/29424.PMC2132683.pdf": {"url_count": 1, "annot_urls": [], "text_urls": ["https://www.jcb.org"], "all_urls": ["https://www.jcb.org"]}, "oa_pdf/6e/17/12530.PMC2132684.pdf": {"url_count": 1, "annot_urls": [], "text_urls": ["https://www.jcb.org"], "all_urls": ["https://www.jcb.org"]}, "oa_pdf/17/6a/12460.PMC2132685.pdf": {"url_count": 1, "annot_urls": [], "text_urls": ["https://www.jcb.org"], "all_urls": ["https://www.jcb.org"]}, "oa_pdf/06/0c/32964.PMC2132686.pdf": {"url_count": 1, "annot_urls": [], "text_urls": ["https://www.jcb.org"], "all_urls": ["https://www.jcb.org"]}, "oa_pdf/22/61/12480.PMC2132687.pdf": {"url_count": 1, "annot_urls": [], "text_urls": ["https://www.jcb.org"], "all_urls": ["https://www.jcb.org"]}, "oa_pdf/97/eb/15053.PMC2132688.pdf": {"url_count": 3, "annot_urls": [], "text_urls": ["https://www.ebi.ac.uk/services/services.html", "https://www.jcb.org", "https://dot.imgen.bcm.tmc.edu:9331/seq-search/struc-predict.html"], "all_urls": ["https://dot.imgen.bcm.tmc.edu:9331/seq-search/struc-predict.html", "https://www.ebi.ac.uk/services/services.html", "https://www.jcb.org"]}, "oa_pdf/a7/93/12490.PMC2132689.pdf": {"url_count": 1, "annot_urls": [], "text_urls": ["https://www.jcb.org"], "all_urls": ["https://www.jcb.org"]}, "oa_pdf/5d/a7/14611.PMC2132690.pdf": {"url_count": 1, "annot_urls": [], "text_urls": ["https://www.jcb.org"], "all_urls": ["https://www.jcb.org"]}, "oa_pdf/2b/50/29398.PMC2132691.pdf": {"url_count": 1, "annot_urls": [], "text_urls": ["https://www.jcb.org"], "all_urls": ["https://www.jcb.org"]}, "oa_pdf/64/f0/15031.PMC2132692.pdf": {"url_count": 1, "annot_urls": [], "text_urls": ["https://www.jcb.org"], "all_urls": ["https://www.jcb.org"]}, "oa_pdf/cf/f3/32988.PMC2132693.pdf": {"url_count": 1, "annot_urls": [], "text_urls": ["https://www.jcb.org"], "all_urls": ["https://www.jcb.org"]}, "oa_pdf/98/72/14697.PMC2132694.pdf": {"url_count": 1, "annot_urls": [], "text_urls": ["https://www.jcb.org"], "all_urls": ["https://www.jcb.org"]}, "oa_pdf/87/f6/32957.PMC2132695.pdf": {"url_count": 1, "annot_urls": [], "text_urls": ["https://www.jcb.org"], "all_urls": ["https://www.jcb.org"]}, "oa_pdf/b1/28/14701.PMC2132696.pdf": {"url_count": 1, "annot_urls": [], "text_urls": ["https://www.jcb.org"], "all_urls": ["https://www.jcb.org"]}, "oa_pdf/a0/2f/15047.PMC2132697.pdf": {"url_count": 1, "annot_urls": [], "text_urls": ["https://www.jcb.org"], "all_urls": ["https://www.jcb.org"]}, "oa_pdf/2a/47/29400.PMC2132698.pdf": {"url_count": 1, "annot_urls": [], "text_urls": ["https://www.jcb.org"], "all_urls": ["https://www.jcb.org"]}, "oa_pdf/99/1d/15066.PMC2132699.pdf": {"url_count": 1, "annot_urls": [], "text_urls": ["https://www.jcb.org"], "all_urls": ["https://www.jcb.org"]}, "oa_pdf/4f/da/29293.PMC2132700.pdf": {"url_count": 1, "annot_urls": [], "text_urls": ["https://www.jcb.org"], "all_urls": ["https://www.jcb.org"]}, "oa_pdf/7e/bb/29327.PMC2132701.pdf": {"url_count": 1, "annot_urls": [], "text_urls": ["https://www.jcb.org"], "all_urls": ["https://www.jcb.org"]}, "oa_pdf/98/bf/14638.PMC2132703.pdf": {"url_count": 1, "annot_urls": [], "text_urls": ["https://www.jcb.org"], "all_urls": ["https://www.jcb.org"]}, "oa_pdf/d8/23/32951.PMC2132704.pdf": {"url_count": 1, "annot_urls": [], "text_urls": ["https://www.jcb.org"], "all_urls": ["https://www.jcb.org"]}, "oa_pdf/2c/74/29289.PMC2132705.pdf": {"url_count": 1, "annot_urls": [], "text_urls": ["https://www.jcb.org"], "all_urls": ["https://www.jcb.org"]}, "oa_pdf/e5/fc/15016.PMC2132706.pdf": {"url_count": 1, "annot_urls": [], "text_urls": ["https://www.jcb.org"], "all_urls": ["https://www.jcb.org"]}, "oa_pdf/8f/64/33004.PMC2132707.pdf": {"url_count": 2, "annot_urls": [], "text_urls": ["https://www.informatics.jax.org", "https://www.jcb.org"], "all_urls": ["https://www.informatics.jax.org", "https://www.jcb.org"]}, "oa_pdf/f4/8b/32919.PMC2132708.pdf": {"url_count": 1, "annot_urls": [], "text_urls": ["https://www.jcb.org"], "all_urls": ["https://www.jcb.org"]}, "oa_pdf/6c/34/14530.PMC2132709.pdf": {"url_count": 1, "annot_urls": [], "text_urls": ["https://www.jcb.org"], "all_urls": ["https://www.jcb.org"]}, "oa_pdf/6c/7f/97-1865.PMC2212164.pdf": {"url_count": 1, "annot_urls": [], "text_urls": ["https://www.jem.org"], "all_urls": ["https://www.jem.org"]}, "oa_pdf/d3/d3/97-1392.PMC2212165.pdf": {"url_count": 1, "annot_urls": [], "text_urls": ["https://www.jem.org"], "all_urls": ["https://www.jem.org"]}, "oa_pdf/d2/24/97-1270.PMC2212166.pdf": {"url_count": 1, "annot_urls": [], "text_urls": ["https://www.jem.org"], "all_urls": ["https://www.jem.org"]}, "oa_pdf/da/e7/97-1635.PMC2212167.pdf": {"url_count": 1, "annot_urls": [], "text_urls": ["https://www.jem.org"], "all_urls": ["https://www.jem.org"]}, "oa_pdf/7d/ca/97-1641.PMC2212168.pdf": {"url_count": 1, "annot_urls": [], "text_urls": ["https://www.jem.org"], "all_urls": ["https://www.jem.org"]}, "oa_pdf/82/2a/97-1599.PMC2212169.pdf": {"url_count": 1, "annot_urls": [], "text_urls": ["https://www.jem.org"], "all_urls": ["https://www.jem.org"]}, "oa_pdf/ec/9c/97-1723.PMC2212170.pdf": {"url_count": 1, "annot_urls": [], "text_urls": ["https://www.jem.org"], "all_urls": ["https://www.jem.org"]}, "oa_pdf/66/55/97-1860.PMC2212171.pdf": {"url_count": 1, "annot_urls": [], "text_urls": ["https://www.jem.org"], "all_urls": ["https://www.jem.org"]}, "oa_pdf/91/b2/97-1749.PMC2212172.pdf": {"url_count": 1, "annot_urls": [], "text_urls": ["https://www.jem.org"], "all_urls": ["https://www.jem.org"]}, "oa_pdf/09/89/97-1911.PMC2212173.pdf": {"url_count": 1, "annot_urls": [], "text_urls": ["https://www.jem.org"], "all_urls": ["https://www.jem.org"]}, "oa_pdf/ed/d1/97-1796.PMC2212174.pdf": {"url_count": 1, "annot_urls": [], "text_urls": ["https://www.jem.org"], "all_urls": ["https://www.jem.org"]}, "oa_pdf/03/25/97-0429.PMC2212175.pdf": {"url_count": 1, "annot_urls": [], "text_urls": ["https://www.jem.org"], "all_urls": ["https://www.jem.org"]}, "oa_pdf/92/2c/97-1103.PMC2212176.pdf": {"url_count": 1, "annot_urls": [], "text_urls": ["https://www.jem.org"], "all_urls": ["https://www.jem.org"]}, "oa_pdf/d3/03/97-1925.PMC2212177.pdf": {"url_count": 1, "annot_urls": [], "text_urls": ["https://www.jem.org"], "all_urls": ["https://www.jem.org"]}, "oa_pdf/b0/e0/97-2258.PMC2212178.pdf": {"url_count": 2, "annot_urls": [], "text_urls": ["https://www.jem.org", "https://prowl.rockefeller.edu"], "all_urls": ["https://prowl.rockefeller.edu", "https://www.jem.org"]}, "oa_pdf/f5/08/97-2059.PMC2212179.pdf": {"url_count": 1, "annot_urls": [], "text_urls": ["https://www.jem.org"], "all_urls": ["https://www.jem.org"]}, "oa_pdf/10/94/97-1995.PMC2212180.pdf": {"url_count": 1, "annot_urls": [], "text_urls": ["https://www.jem.org"], "all_urls": ["https://www.jem.org"]}, "oa_pdf/43/85/97-2111.PMC2212181.pdf": {"url_count": 1, "annot_urls": [], "text_urls": ["https://www.jem.org"], "all_urls": ["https://www.jem.org"]}, "oa_pdf/12/2b/97-2108.PMC2212182.pdf": {"url_count": 1, "annot_urls": [], "text_urls": ["https://www.jem.org"], "all_urls": ["https://www.jem.org"]}, "oa_pdf/b6/95/97-2137.PMC2212183.pdf": {"url_count": 1, "annot_urls": [], "text_urls": ["https://www.jem.org"], "all_urls": ["https://www.jem.org"]}, "oa_pdf/6b/01/97-1353.PMC2212184.pdf": {"url_count": 1, "annot_urls": [], "text_urls": ["https://www.jem.org"], "all_urls": ["https://www.jem.org"]}, "oa_pdf/39/9f/97-1878.PMC2212185.pdf": {"url_count": 1, "annot_urls": [], "text_urls": ["https://www.jem.org"], "all_urls": ["https://www.jem.org"]}, "oa_pdf/cd/cc/97-1568.PMC2212186.pdf": {"url_count": 1, "annot_urls": [], "text_urls": ["https://www.jem.org"], "all_urls": ["https://www.jem.org"]}, "oa_pdf/4b/26/97-1974.PMC2212187.pdf": {"url_count": 1, "annot_urls": [], "text_urls": ["https://www.jem.org"], "all_urls": ["https://www.jem.org"]}, "oa_pdf/f7/82/97-2028.PMC2212188.pdf": {"url_count": 1, "annot_urls": [], "text_urls": ["https://www.jem.org"], "all_urls": ["https://www.jem.org"]}, "oa_pdf/c4/20/97-1703.PMC2212189.pdf": {"url_count": 1, "annot_urls": [], "text_urls": ["https://www.jem.org"], "all_urls": ["https://www.jem.org"]}, "oa_pdf/d9/f0/97-1965.PMC2212190.pdf": {"url_count": 1, "annot_urls": [], "text_urls": ["https://www.jem.org"], "all_urls": ["https://www.jem.org"]}, "oa_pdf/a6/1e/97-1053.PMC2212191.pdf": {"url_count": 1, "annot_urls": [], "text_urls": ["https://www.jem.org"], "all_urls": ["https://www.jem.org"]}, "oa_pdf/42/9e/97-2043.PMC2212192.pdf": {"url_count": 1, "annot_urls": [], "text_urls": ["https://www.jem.org"], "all_urls": ["https://www.jem.org"]}, "oa_pdf/02/06/97-1293.PMC2212193.pdf": {"url_count": 1, "annot_urls": [], "text_urls": ["https://www.jem.org"], "all_urls": ["https://www.jem.org"]}, "oa_pdf/30/3d/97-1570.PMC2212194.pdf": {"url_count": 1, "annot_urls": [], "text_urls": ["https://www.jem.org"], "all_urls": ["https://www.jem.org"]}, "oa_pdf/30/00/97-1185.PMC2212195.pdf": {"url_count": 1, "annot_urls": [], "text_urls": ["https://www.jem.org"], "all_urls": ["https://www.jem.org"]}, "oa_pdf/42/57/98-C001.PMC2212197.pdf": {"url_count": 1, "annot_urls": [], "text_urls": ["https://www.jem.org"], "all_urls": ["https://www.jem.org"]}, "oa_pdf/c6/b2/GP-7548.PMC2217112.pdf": {"url_count": 1, "annot_urls": [], "text_urls": ["https://www.jgp.org"], "all_urls": ["https://www.jgp.org"]}, "oa_pdf/8d/60/GP-7619.PMC2217113.pdf": {"url_count": 1, "annot_urls": [], "text_urls": ["https://www.jgp.org"], "all_urls": ["https://www.jgp.org"]}, "oa_pdf/da/93/GP-7620.PMC2217114.pdf": {"url_count": 1, "annot_urls": [], "text_urls": ["https://www.jgp.org"], "all_urls": ["https://www.jgp.org"]}, "oa_pdf/4b/7e/GP-7591.PMC2217115.pdf": {"url_count": 1, "annot_urls": [], "text_urls": ["https://www.jgp.org"], "all_urls": ["https://www.jgp.org"]}, "oa_pdf/99/af/GP-7596.PMC2217116.pdf": {"url_count": 1, "annot_urls": [], "text_urls": ["https://www.jgp.org"], "all_urls": ["https://www.jgp.org"]}, "oa_pdf/31/2a/GP-7640.PMC2217117.pdf": {"url_count": 1, "annot_urls": [], "text_urls": ["https://www.jgp.org"], "all_urls": ["https://www.jgp.org"]}, "oa_pdf/8f/77/indmedgaz71357-0011.PMC5140917.pdf": {"url_count": 0, "annot_urls": [], "text_urls": [], "all_urls": []}, "oa_pdf/90/de/indmedgaz71357-0026.PMC5140918.pdf": {"url_count": 0, "annot_urls": [], "text_urls": [], "all_urls": []}, "oa_pdf/78/f3/indmedgaz71357-0025b.PMC5140919.pdf": {"url_count": 0, "annot_urls": [], "text_urls": [], "all_urls": []}, "oa_pdf/72/e5/indmedgaz71357-0023.PMC5140920.pdf": {"url_count": 0, "annot_urls": [], "text_urls": [], "all_urls": []}, "oa_pdf/ec/8f/indmedgaz71357-0003a.PMC5140921.pdf": {"url_count": 0, "annot_urls": [], "text_urls": [], "all_urls": []}, "oa_pdf/dc/7b/indmedgaz71357-0006.PMC5140922.pdf": {"url_count": 0, "annot_urls": [], "text_urls": [], "all_urls": []}, "oa_pdf/be/c2/indmedgaz71357-0039b.PMC5140923.pdf": {"url_count": 0, "annot_urls": [], "text_urls": [], "all_urls": []}, "oa_pdf/0e/f0/indmedgaz71357-0027b.PMC5140925.pdf": {"url_count": 0, "annot_urls": [], "text_urls": [], "all_urls": []}, "oa_pdf/6d/95/indmedgaz71357-0020b.PMC5140926.pdf": {"url_count": 0, "annot_urls": [], "text_urls": [], "all_urls": []}, "oa_pdf/15/ec/indmedgaz71357-0039a.PMC5140927.pdf": {"url_count": 0, "annot_urls": [], "text_urls": [], "all_urls": []}, "oa_pdf/f8/2a/indmedgaz71357-0027a.PMC5140928.pdf": {"url_count": 0, "annot_urls": [], "text_urls": [], "all_urls": []}, "oa_pdf/96/0a/indmedgaz71357-0033.PMC5140929.pdf": {"url_count": 0, "annot_urls": [], "text_urls": [], "all_urls": []}, "oa_pdf/36/b7/indmedgaz71357-0030.PMC5140930.pdf": {"url_count": 0, "annot_urls": [], "text_urls": [], "all_urls": []}, "oa_pdf/9c/13/indmedgaz71357-0021b.PMC5140931.pdf": {"url_count": 0, "annot_urls": [], "text_urls": [], "all_urls": []}, "oa_pdf/a6/94/indmedgaz71357-0019.PMC5140932.pdf": {"url_count": 0, "annot_urls": [], "text_urls": [], "all_urls": []}, "oa_pdf/07/80/indmedgaz71357-0028a.PMC5140933.pdf": {"url_count": 0, "annot_urls": [], "text_urls": [], "all_urls": []}, "oa_pdf/cf/3b/indmedgaz71357-0039c.PMC5140935.pdf": {"url_count": 0, "annot_urls": [], "text_urls": [], "all_urls": []}, "oa_pdf/46/73/indmedgaz71357-0001.PMC5140936.pdf": {"url_count": 0, "annot_urls": [], "text_urls": [], "all_urls": []}, "oa_pdf/6b/cf/indmedgaz71357-0040a.PMC5140939.pdf": {"url_count": 0, "annot_urls": [], "text_urls": [], "all_urls": []}, "oa_pdf/ac/9c/indmedgaz71357-0020a.PMC5140940.pdf": {"url_count": 0, "annot_urls": [], "text_urls": [], "all_urls": []}, "oa_pdf/cf/55/indmedgaz71357-0022.PMC5140941.pdf": {"url_count": 0, "annot_urls": [], "text_urls": [], "all_urls": []}, "oa_pdf/e9/a7/indmedgaz71357-0003b.PMC5140942.pdf": {"url_count": 0, "annot_urls": [], "text_urls": [], "all_urls": []}, "oa_pdf/50/b3/indmedgaz71357-0028b.PMC5140943.pdf": {"url_count": 0, "annot_urls": [], "text_urls": [], "all_urls": []}, "oa_pdf/f0/82/indmedgaz71357-0032.PMC5140944.pdf": {"url_count": 0, "annot_urls": [], "text_urls": [], "all_urls": []}, "oa_pdf/08/17/indmedgaz71357-0038.PMC5140945.pdf": {"url_count": 0, "annot_urls": [], "text_urls": [], "all_urls": []}, "oa_pdf/bd/f4/indmedgaz71357-0027c.PMC5140946.pdf": {"url_count": 0, "annot_urls": [], "text_urls": [], "all_urls": []}, "oa_pdf/94/35/indmedgaz71357-0036.PMC5140947.pdf": {"url_count": 0, "annot_urls": [], "text_urls": [], "all_urls": []}, "oa_pdf/2f/c7/indmedgaz71357-0025a.PMC5140948.pdf": {"url_count": 0, "annot_urls": [], "text_urls": [], "all_urls": []}, "oa_pdf/5d/90/glasgowmedj75351-0001.PMC5949780.pdf": {"url_count": 0, "annot_urls": [], "text_urls": [], "all_urls": []}, "oa_pdf/15/36/glasgowmedj75351-0074.PMC5949781.pdf": {"url_count": 0, "annot_urls": [], "text_urls": [], "all_urls": []}, "oa_pdf/c6/dd/glasgowmedj75351-0023.PMC5949782.pdf": {"url_count": 0, "annot_urls": [], "text_urls": [], "all_urls": []}, "oa_pdf/42/df/glasgowmedj75351-0035.PMC5949784.pdf": {"url_count": 0, "annot_urls": [], "text_urls": [], "all_urls": []}, "oa_pdf/ef/1b/glasgowmedj75351-0055.PMC5949785.pdf": {"url_count": 0, "annot_urls": [], "text_urls": [], "all_urls": []}, "oa_pdf/73/bb/glasgowmedj75351-0020.PMC5949786.pdf": {"url_count": 0, "annot_urls": [], "text_urls": [], "all_urls": []}, "oa_pdf/07/1c/glasgowmedj75351-0071.PMC5949787.pdf": {"url_count": 0, "annot_urls": [], "text_urls": [], "all_urls": []}, "oa_pdf/1d/b0/glasgowmedj75351-0077.PMC5949788.pdf": {"url_count": 0, "annot_urls": [], "text_urls": [], "all_urls": []}, "oa_pdf/05/10/glasgowmedj75351-0080.PMC5949791.pdf": {"url_count": 0, "annot_urls": [], "text_urls": [], "all_urls": []}, "oa_pdf/0f/40/glasgowmedj75351-0019.PMC5949792.pdf": {"url_count": 0, "annot_urls": [], "text_urls": [], "all_urls": []}, "oa_pdf/0f/16/glasgowmedj75351-0059.PMC5949793.pdf": {"url_count": 0, "annot_urls": [], "text_urls": [], "all_urls": []}, "oa_pdf/93/8b/glasgowmedj75351-0011.PMC5949794.pdf": {"url_count": 0, "annot_urls": [], "text_urls": [], "all_urls": []}, "oa_pdf/81/fe/glasgowmedj75351-0006.PMC5949795.pdf": {"url_count": 0, "annot_urls": [], "text_urls": [], "all_urls": []}}, "num_files": 350}}