{"200211": {"files": {"oa_pdf/dd/dd/200205086.PMC2173062.pdf": {"url_count": 1, "annot_urls": [], "text_urls": ["https://www.jcb.org/cgi/doi/10.1083/jcb.200205086"], "all_urls": ["https://www.jcb.org/cgi/doi/10.1083/jcb.200205086"]}, "oa_pdf/2e/57/200207138.PMC2173063.pdf": {"url_count": 1, "annot_urls": [], "text_urls": ["https://www.jcb.org/cgi/doi/10.1083/jcb.200207138"], "all_urls": ["https://www.jcb.org/cgi/doi/10.1083/jcb.200207138"]}, "oa_pdf/28/46/200210024.PMC2173064.pdf": {"url_count": 1, "annot_urls": [], "text_urls": ["https://www.jcb.org/cgi/doi/10.1083/jcb.200210024"], "all_urls": ["https://www.jcb.org/cgi/doi/10.1083/jcb.200210024"]}, "oa_pdf/d7/8f/200207058.PMC2173065.pdf": {"url_count": 1, "annot_urls": [], "text_urls": ["https://www.jcb.org/cgi/doi/10.1083/jcb.200207058"], "all_urls": ["https://www.jcb.org/cgi/doi/10.1083/jcb.200207058"]}, "oa_pdf/a8/ef/200205039.PMC2173066.pdf": {"url_count": 1, "annot_urls": [], "text_urls": ["https://www.jcb.org/cgi/doi/10.1083/jcb.200205039"], "all_urls": ["https://www.jcb.org/cgi/doi/10.1083/jcb.200205039"]}, "oa_pdf/b4/d1/200207153.PMC2173070.pdf": {"url_count": 1, "annot_urls": [], "text_urls": ["https://www.jcb.org/cgi/doi/10.1083/jcb.200207153"], "all_urls": ["https://www.jcb.org/cgi/doi/10.1083/jcb.200207153"]}, "oa_pdf/63/0a/200205115.PMC2173073.pdf": {"url_count": 1, "annot_urls": [], "text_urls": ["https://www.jcb.org/cgi/doi/10.1083/jcb.200205115"], "all_urls": ["https://www.jcb.org/cgi/doi/10.1083/jcb.200205115"]}, "oa_pdf/a5/55/200203150.PMC2173076.pdf": {"url_count": 1, "annot_urls": [], "text_urls": ["https://www.jcb.org/cgi"], "all_urls": ["https://www.jcb.org/cgi"]}, "oa_pdf/88/41/200206020.PMC2173077.pdf": {"url_count": 1, "annot_urls": [], "text_urls": ["https://www.jcb.org/cgi/doi/10.1083/jcb.200206020"], "all_urls": ["https://www.jcb.org/cgi/doi/10.1083/jcb.200206020"]}, "oa_pdf/2e/06/200208037.PMC2173079.pdf": {"url_count": 1, "annot_urls": [], "text_urls": ["https://www.jcb.org/cgi/doi/10.1083/jcb.200208037"], "all_urls": ["https://www.jcb.org/cgi/doi/10.1083/jcb.200208037"]}, "oa_pdf/20/65/200207174.PMC2173080.pdf": {"url_count": 1, "annot_urls": [], "text_urls": ["https://www.jcb.org/cgi/doi/10.1083/jcb.200207174"], "all_urls": ["https://www.jcb.org/cgi/doi/10.1083/jcb.200207174"]}, "oa_pdf/ba/9f/200205026.PMC2173082.pdf": {"url_count": 2, "annot_urls": [], "text_urls": ["https://www.jcb.org/cgi/doi/10.1083/jcb.200205026", "https://www.jcb.org/cgi/content"], "all_urls": ["https://www.jcb.org/cgi/content", "https://www.jcb.org/cgi/doi/10.1083/jcb.200205026"]}, "oa_pdf/85/31/200204144.PMC2173083.pdf": {"url_count": 1, "annot_urls": [], "text_urls": ["https://www.jcb.org/cgi/doi/10.1083/jcb.200204144"], "all_urls": ["https://www.jcb.org/cgi/doi/10.1083/jcb.200204144"]}, "oa_pdf/8d/1a/200205089.PMC2173087.pdf": {"url_count": 1, "annot_urls": [], "text_urls": ["https://www.jcb.org/cgi/doi/10.1083/jcb.200205089"], "all_urls": ["https://www.jcb.org/cgi/doi/10.1083/jcb.200205089"]}, "oa_pdf/f2/3f/200208001.PMC2173089.pdf": {"url_count": 2, "annot_urls": [], "text_urls": ["https://www.jcb.org/cgi", "https://www.ncbi.nlm.nih.gov/;"], "all_urls": ["https://www.jcb.org/cgi", "https://www.ncbi.nlm.nih.gov/;"]}, "oa_pdf/f5/a2/200207128.PMC2173090.pdf": {"url_count": 2, "annot_urls": [], "text_urls": ["https://flybase.bio.indiana.edu", "https://www.jcb.org/cgi/doi/10.1083/jcb.200207128"], "all_urls": ["https://flybase.bio.indiana.edu", "https://www.jcb.org/cgi/doi/10.1083/jcb.200207128"]}, "oa_pdf/9d/6a/200207090.PMC2173091.pdf": {"url_count": 1, "annot_urls": [], "text_urls": ["https://www.jcb.org/cgi/doi/10.1083/jcb.200207090"], "all_urls": ["https://www.jcb.org/cgi/doi/10.1083/jcb.200207090"]}, "oa_pdf/1a/40/200208154.PMC2173094.pdf": {"url_count": 2, "annot_urls": [], "text_urls": ["https://www.jcb.org/cgi/content/full/j", "https://www.jcb.org/cgi/doi/10.1083/jcb.200208154"], "all_urls": ["https://www.jcb.org/cgi/content/full/j", "https://www.jcb.org/cgi/doi/10.1083/jcb.200208154"]}, "oa_pdf/d1/8b/200205098.PMC2173095.pdf": {"url_count": 1, "annot_urls": [], "text_urls": ["https://www.jcb.org/cgi"], "all_urls": ["https://www.jcb.org/cgi"]}, "oa_pdf/cc/37/15941.PMC2173096.pdf": {"url_count": 0, "annot_urls": [], "text_urls": [], "all_urls": []}, "oa_pdf/60/a5/200208058.PMC2173097.pdf": {"url_count": 1, "annot_urls": [], "text_urls": ["https://www.jcb.org/cgi/doi/10.1083/jcb.200208058"], "all_urls": ["https://www.jcb.org/cgi/doi/10.1083/jcb.200208058"]}, "oa_pdf/8c/be/200204153.PMC2173098.pdf": {"url_count": 1, "annot_urls": [], "text_urls": ["https://www.jcb.org/cgi/doi/10.1083/jcb.200204153"], "all_urls": ["https://www.jcb.org/cgi/doi/10.1083/jcb.200204153"]}, "oa_pdf/74/a7/200206024.PMC2173099.pdf": {"url_count": 1, "annot_urls": [], "text_urls": ["https://www.jcb.org/cgi/doi/10.1083/jcb.200206024"], "all_urls": ["https://www.jcb.org/cgi/doi/10.1083/jcb.200206024"]}, "oa_pdf/44/2c/200204102.PMC2173100.pdf": {"url_count": 2, "annot_urls": [], "text_urls": ["https://www.jcb.org/cgi/doi/10.1083/jcb.200204102", "https://www.ncbi.nlm.nih.gov/omim;Fra"], "all_urls": ["https://www.jcb.org/cgi/doi/10.1083/jcb.200204102", "https://www.ncbi.nlm.nih.gov/omim;Fra"]}, "oa_pdf/76/33/200205084.PMC2173104.pdf": {"url_count": 1, "annot_urls": [], "text_urls": ["https://www.jcb.org/cgi/doi/10.1083/jcb.200205084"], "all_urls": ["https://www.jcb.org/cgi/doi/10.1083/jcb.200205084"]}, "oa_pdf/08/22/200202117.PMC2173105.pdf": {"url_count": 1, "annot_urls": [], "text_urls": ["https://www.jcb.org/cgi/doi/10.1083/jcb.200202117"], "all_urls": ["https://www.jcb.org/cgi/doi/10.1083/jcb.200202117"]}, "oa_pdf/c4/79/200204065.PMC2173107.pdf": {"url_count": 1, "annot_urls": [], "text_urls": ["https://www.jc"], "all_urls": ["https://www.jc"]}, "oa_pdf/4c/53/200205091.PMC2173108.pdf": {"url_count": 1, "annot_urls": [], "text_urls": ["https://www.jcb.org/cgi/doi/10.1083/jcb.200205091"], "all_urls": ["https://www.jcb.org/cgi/doi/10.1083/jcb.200205091"]}, "oa_pdf/76/ae/200208013.PMC2173109.pdf": {"url_count": 2, "annot_urls": [], "text_urls": ["https://www.jcb.org/cgi/content/ful", "https://www.jcb.org/cgi/doi/10.1083/jcb.200208013"], "all_urls": ["https://www.jcb.org/cgi/content/ful", "https://www.jcb.org/cgi/doi/10.1083/jcb.200208013"]}, "oa_pdf/a0/9f/200208159.PMC2173110.pdf": {"url_count": 1, "annot_urls": [], "text_urls": ["https://www.jcb.org/cgi/doi/10.1083/jcb.200208159"], "all_urls": ["https://www.jcb.org/cgi/doi/10.1083/jcb.200208159"]}, "oa_pdf/0e/08/20021017.PMC2193981.pdf": {"url_count": 1, "annot_urls": [], "text_urls": ["https://www.jem.org/cgi/doi/10.1084/jem.20021017"], "all_urls": ["https://www.jem.org/cgi/doi/10.1084/jem.20021017"]}, "oa_pdf/dc/7b/20021139.PMC2193983.pdf": {"url_count": 1, "annot_urls": [], "text_urls": ["https://www.jem.org/cgi/doi/10.1084/jem.20021139"], "all_urls": ["https://www.jem.org/cgi/doi/10.1084/jem.20021139"]}, "oa_pdf/4e/e2/20020562.PMC2193984.pdf": {"url_count": 1, "annot_urls": [], "text_urls": ["https://www.jem.org/cgi/doi/10.1084/jem.20020562"], "all_urls": ["https://www.jem.org/cgi/doi/10.1084/jem.20020562"]}, "oa_pdf/73/5c/20021129.PMC2193985.pdf": {"url_count": 1, "annot_urls": [], "text_urls": ["https://www.jem.org/cgi/doi/10.1084/jem.20021129"], "all_urls": ["https://www.jem.org/cgi/doi/10.1084/jem.20021129"]}, "oa_pdf/71/47/20021196.PMC2193986.pdf": {"url_count": 1, "annot_urls": [], "text_urls": ["https://www.jem.org/cgi/doi/10.1084/jem.20021196"], "all_urls": ["https://www.jem.org/cgi/doi/10.1084/jem.20021196"]}, "oa_pdf/31/9d/20020890.PMC2193987.pdf": {"url_count": 1, "annot_urls": [], "text_urls": ["https://www.jem.org/cgi/doi/10.1084/jem.20020890"], "all_urls": ["https://www.jem.org/cgi/doi/10.1084/jem.20020890"]}, "oa_pdf/18/e5/20012135.PMC2193988.pdf": {"url_count": 1, "annot_urls": [], "text_urls": ["https://www.jem.org/cgi/doi/10.1084/jem.20012135"], "all_urls": ["https://www.jem.org/cgi/doi/10.1084/jem.20012135"]}, "oa_pdf/4d/ac/20021031.PMC2193989.pdf": {"url_count": 1, "annot_urls": [], "text_urls": ["https://www.jem.org/cgi/doi/10.1084/jem.20021031"], "all_urls": ["https://www.jem.org/cgi/doi/10.1084/jem.20021031"]}, "oa_pdf/fd/1d/20020943.PMC2193991.pdf": {"url_count": 1, "annot_urls": [], "text_urls": ["https://www.jem.org/cgi/doi/10.1084/jem.20020943"], "all_urls": ["https://www.jem.org/cgi/doi/10.1084/jem.20020943"]}, "oa_pdf/ee/51/20020649.PMC2193992.pdf": {"url_count": 1, "annot_urls": [], "text_urls": ["https://www.jem.org/cgi/doi/10.1084/jem.20020649"], "all_urls": ["https://www.jem.org/cgi/doi/10.1084/jem.20020649"]}, "oa_pdf/89/0c/20021572.PMC2193993.pdf": {"url_count": 1, "annot_urls": [], "text_urls": ["https://www.jem.org/cgi/doi/10.1084/jem.20021572"], "all_urls": ["https://www.jem.org/cgi/doi/10.1084/jem.20021572"]}, "oa_pdf/1b/65/20021183.PMC2194099.pdf": {"url_count": 1, "annot_urls": [], "text_urls": ["https://www.jem.org/cgi/doi/10.1084/jem.20021183"], "all_urls": ["https://www.jem.org/cgi/doi/10.1084/jem.20021183"]}, "oa_pdf/db/01/20021758.PMC2194100.pdf": {"url_count": 1, "annot_urls": [], "text_urls": ["https://www.jem.org/cgi/doi/10.1084/jem.20021758"], "all_urls": ["https://www.jem.org/cgi/doi/10.1084/jem.20021758"]}, "oa_pdf/2d/21/20020735.PMC2194101.pdf": {"url_count": 1, "annot_urls": [], "text_urls": ["https://www.jem.org/cgi/doi/10.1084/jem.20020735"], "all_urls": ["https://www.jem.org/cgi/doi/10.1084/jem.20020735"]}, "oa_pdf/cc/54/20021167.PMC2194102.pdf": {"url_count": 1, "annot_urls": [], "text_urls": ["https://www.jem.org/cgi/doi/10.1084/jem.20021167"], "all_urls": ["https://www.jem.org/cgi/doi/10.1084/jem.20021167"]}, "oa_pdf/8c/d9/20020390.PMC2194103.pdf": {"url_count": 1, "annot_urls": [], "text_urls": ["https://www.jem.org/cgi/doi/10.1084/jem.20020390"], "all_urls": ["https://www.jem.org/cgi/doi/10.1084/jem.20020390"]}, "oa_pdf/f0/c8/20010916.PMC2194104.pdf": {"url_count": 1, "annot_urls": [], "text_urls": ["https://www.jem.org/cgi/doi/10.1084/jem.20010916"], "all_urls": ["https://www.jem.org/cgi/doi/10.1084/jem.20010916"]}, "oa_pdf/da/48/20020885.PMC2194105.pdf": {"url_count": 1, "annot_urls": [], "text_urls": ["https://www.jem.org/cgi/doi/10.1084/jem.20020885"], "all_urls": ["https://www.jem.org/cgi/doi/10.1084/jem.20020885"]}, "oa_pdf/3e/ef/20020762.PMC2194106.pdf": {"url_count": 1, "annot_urls": [], "text_urls": ["https://www.jem.org/cgi/doi/10.1084/jem.20020762"], "all_urls": ["https://www.jem.org/cgi/doi/10.1084/jem.20020762"]}, "oa_pdf/ec/6d/20021110.PMC2194107.pdf": {"url_count": 1, "annot_urls": [], "text_urls": ["https://www.jem.org/cgi/doi/10.1084/jem.20021110"], "all_urls": ["https://www.jem.org/cgi/doi/10.1084/jem.20021110"]}, "oa_pdf/4b/b7/20020824.PMC2194108.pdf": {"url_count": 1, "annot_urls": [], "text_urls": ["https://www.jem.org/cgi/doi/10.1084/jem.20020824"], "all_urls": ["https://www.jem.org/cgi/doi/10.1084/jem.20020824"]}, "oa_pdf/6d/23/20021074.PMC2194109.pdf": {"url_count": 1, "annot_urls": [], "text_urls": ["https://www.jem.org/cgi/doi/10.1084/jem.20021074"], "all_urls": ["https://www.jem.org/cgi/doi/10.1084/jem.20021074"]}, "oa_pdf/07/fa/20011247.PMC2194110.pdf": {"url_count": 1, "annot_urls": [], "text_urls": ["https://www.jem.org/cgi/doi/10.1084/jem.20011247"], "all_urls": ["https://www.jem.org/cgi/doi/10.1084/jem.20011247"]}, "oa_pdf/92/59/20020324.PMC2194111.pdf": {"url_count": 1, "annot_urls": [], "text_urls": ["https://www.jem.org/cgi/doi/10.1084/jem.20020324"], "all_urls": ["https://www.jem.org/cgi/doi/10.1084/jem.20020324"]}, "oa_pdf/f7/b4/20028641.PMC2229549.pdf": {"url_count": 1, "annot_urls": [], "text_urls": ["https://www.jgp.org/cgi/doi/10.1085/jgp.200308804"], "all_urls": ["https://www.jgp.org/cgi/doi/10.1085/jgp.200308804"]}, "oa_pdf/66/26/20028677.PMC2229550.pdf": {"url_count": 1, "annot_urls": [], "text_urls": ["https://www.jgp.org/cgi/doi/10.1085/jgp.20028677"], "all_urls": ["https://www.jgp.org/cgi/doi/10.1085/jgp.20028677"]}, "oa_pdf/dc/52/20028679.PMC2229551.pdf": {"url_count": 1, "annot_urls": [], "text_urls": ["https://www.jgp.org/cgi/doi/10.1085/jgp.20028679"], "all_urls": ["https://www.jgp.org/cgi/doi/10.1085/jgp.20028679"]}, "oa_pdf/14/06/20028696.PMC2229552.pdf": {"url_count": 1, "annot_urls": [], "text_urls": ["https://www.jgp.org/cgi/doi/10.1085/jgp.20028696"], "all_urls": ["https://www.jgp.org/cgi/doi/10.1085/jgp.20028696"]}, "oa_pdf/a1/c1/20028631.PMC2229553.pdf": {"url_count": 1, "annot_urls": [], "text_urls": ["https://www.jgp.org/cgi/doi/10.1085/jgp.20028631"], "all_urls": ["https://www.jgp.org/cgi/doi/10.1085/jgp.20028631"]}, "oa_pdf/bf/7d/20028645.PMC2229554.pdf": {"url_count": 1, "annot_urls": [], "text_urls": ["https://www.jgp.org/cgi/doi/10.1085/jgp.20028645"], "all_urls": ["https://www.jgp.org/cgi/doi/10.1085/jgp.20028645"]}, "oa_pdf/a0/29/20028687.PMC2229555.pdf": {"url_count": 1, "annot_urls": [], "text_urls": ["https://www.jgp.org/cgi/doi/10.1085/jgp.20028687"], "all_urls": ["https://www.jgp.org/cgi/doi/10.1085/jgp.20028687"]}, "oa_pdf/ac/5e/20028663.PMC2229556.pdf": {"url_count": 2, "annot_urls": [], "text_urls": ["https://www.jgp.org/cgi/doi/10.1085/jgp.20028663", "https://www.stanford"], "all_urls": ["https://www.jgp.org/cgi/doi/10.1085/jgp.20028663", "https://www.stanford"]}, "oa_pdf/2c/99/20028685.PMC2229557.pdf": {"url_count": 1, "annot_urls": [], "text_urls": ["https://www.jgp.org/cgi/doi/10.1085/jgp.20028685"], "all_urls": ["https://www.jgp.org/cgi/doi/10.1085/jgp.20028685"]}, "oa_pdf/05/4a/20028639.PMC2229558.pdf": {"url_count": 1, "annot_urls": [], "text_urls": ["https://www.jgp.org/cgi/doi/10.1085/jgp.20028639"], "all_urls": ["https://www.jgp.org/cgi/doi/10.1085/jgp.20028639"]}, "oa_pdf/d7/66/jcb1590390.PMC2246633.pdf": {"url_count": 0, "annot_urls": [], "text_urls": [], "all_urls": []}, "oa_pdf/c3/36/jcb1590388.PMC2246634.pdf": {"url_count": 0, "annot_urls": [], "text_urls": [], "all_urls": []}, "oa_pdf/72/73/jcb159389a.PMC2246635.pdf": {"url_count": 0, "annot_urls": [], "text_urls": [], "all_urls": []}, "oa_pdf/7d/ed/jcb159390b.PMC2246636.pdf": {"url_count": 0, "annot_urls": [], "text_urls": [], "all_urls": []}, "oa_pdf/9d/2f/jcb159391a.PMC2246637.pdf": {"url_count": 0, "annot_urls": [], "text_urls": [], "all_urls": []}, "oa_pdf/fa/c7/jcb1590391.PMC2246638.pdf": {"url_count": 0, "annot_urls": [], "text_urls": [], "all_urls": []}, "oa_pdf/bb/94/jcb159388a.PMC2246639.pdf": {"url_count": 0, "annot_urls": [], "text_urls": [], "all_urls": []}, "oa_pdf/f6/56/jcb159389b.PMC2246640.pdf": {"url_count": 0, "annot_urls": [], "text_urls": [], "all_urls": []}, "oa_pdf/41/e2/jcb159390a.PMC2246641.pdf": {"url_count": 0, "annot_urls": [], "text_urls": [], "all_urls": []}, "oa_pdf/fa/69/jcb1590389.PMC2246642.pdf": {"url_count": 0, "annot_urls": [], "text_urls": [], "all_urls": []}, "oa_pdf/87/f5/jcb1590539.PMC2246643.pdf": {"url_count": 0, "annot_urls": [], "text_urls": [], "all_urls": []}, "oa_pdf/0d/7d/jcb159536a.PMC2246644.pdf": {"url_count": 0, "annot_urls": [], "text_urls": [], "all_urls": []}, "oa_pdf/a3/51/jcb159536b.PMC2246645.pdf": {"url_count": 0, "annot_urls": [], "text_urls": [], "all_urls": []}, "oa_pdf/92/e9/jcb159538a.PMC2246646.pdf": {"url_count": 0, "annot_urls": [], "text_urls": [], "all_urls": []}, "oa_pdf/5b/7f/jcb1590536.PMC2246647.pdf": {"url_count": 0, "annot_urls": [], "text_urls": [], "all_urls": []}, "oa_pdf/24/0d/jcb159539b.PMC2246648.pdf": {"url_count": 0, "annot_urls": [], "text_urls": [], "all_urls": []}, "oa_pdf/ff/94/jcb1590538.PMC2246649.pdf": {"url_count": 0, "annot_urls": [], "text_urls": [], "all_urls": []}, "oa_pdf/9d/98/jcb159537a.PMC2246650.pdf": {"url_count": 0, "annot_urls": [], "text_urls": [], "all_urls": []}, "oa_pdf/68/40/jcb159539a.PMC2246651.pdf": {"url_count": 0, "annot_urls": [], "text_urls": [], "all_urls": []}, "oa_pdf/c4/a9/jcb1590537.PMC2246652.pdf": {"url_count": 0, "annot_urls": [], "text_urls": [], "all_urls": []}}, "num_files": 84}}