{"193212": {"files": {"oa_pdf/cf/f2/indmedgaz72181-0022b.PMC5231841.pdf": {"url_count": 0, "annot_urls": [], "text_urls": [], "all_urls": []}, "oa_pdf/15/37/indmedgaz72181-0019.PMC5231842.pdf": {"url_count": 0, "annot_urls": [], "text_urls": [], "all_urls": []}, "oa_pdf/72/66/indmedgaz72181-0055e.PMC5231843.pdf": {"url_count": 0, "annot_urls": [], "text_urls": [], "all_urls": []}, "oa_pdf/ea/c3/indmedgaz72181-0054a.PMC5231844.pdf": {"url_count": 0, "annot_urls": [], "text_urls": [], "all_urls": []}, "oa_pdf/86/39/indmedgaz72181-0053.PMC5231845.pdf": {"url_count": 0, "annot_urls": [], "text_urls": [], "all_urls": []}, "oa_pdf/a9/49/indmedgaz72181-0055b.PMC5231846.pdf": {"url_count": 0, "annot_urls": [], "text_urls": [], "all_urls": []}, "oa_pdf/dd/c8/indmedgaz72181-0024.PMC5231847.pdf": {"url_count": 0, "annot_urls": [], "text_urls": [], "all_urls": []}, "oa_pdf/74/6d/indmedgaz72181-0034.PMC5231848.pdf": {"url_count": 0, "annot_urls": [], "text_urls": [], "all_urls": []}, "oa_pdf/04/23/indmedgaz72181-0059c.PMC5231850.pdf": {"url_count": 0, "annot_urls": [], "text_urls": [], "all_urls": []}, "oa_pdf/f0/67/indmedgaz72181-0055d.PMC5231851.pdf": {"url_count": 0, "annot_urls": [], "text_urls": [], "all_urls": []}, "oa_pdf/f8/05/indmedgaz72181-0056c.PMC5231852.pdf": {"url_count": 0, "annot_urls": [], "text_urls": [], "all_urls": []}, "oa_pdf/04/9d/indmedgaz72181-0020.PMC5231853.pdf": {"url_count": 0, "annot_urls": [], "text_urls": [], "all_urls": []}, "oa_pdf/b3/58/indmedgaz72181-0022a.PMC5231854.pdf": {"url_count": 0, "annot_urls": [], "text_urls": [], "all_urls": []}, "oa_pdf/5e/70/indmedgaz72181-0038.PMC5231855.pdf": {"url_count": 0, "annot_urls": [], "text_urls": [], "all_urls": []}, "oa_pdf/f0/ce/indmedgaz72181-0056a.PMC5231856.pdf": {"url_count": 0, "annot_urls": [], "text_urls": [], "all_urls": []}, "oa_pdf/7e/29/indmedgaz72181-0014.PMC5231857.pdf": {"url_count": 0, "annot_urls": [], "text_urls": [], "all_urls": []}, "oa_pdf/69/19/indmedgaz72181-0059a.PMC5231858.pdf": {"url_count": 0, "annot_urls": [], "text_urls": [], "all_urls": []}, "oa_pdf/46/2c/indmedgaz72181-0001.PMC5231860.pdf": {"url_count": 0, "annot_urls": [], "text_urls": [], "all_urls": []}, "oa_pdf/e8/01/indmedgaz72181-0054b.PMC5231861.pdf": {"url_count": 0, "annot_urls": [], "text_urls": [], "all_urls": []}, "oa_pdf/54/97/indmedgaz72181-0059b.PMC5231862.pdf": {"url_count": 0, "annot_urls": [], "text_urls": [], "all_urls": []}, "oa_pdf/f4/94/indmedgaz72181-0047.PMC5231863.pdf": {"url_count": 0, "annot_urls": [], "text_urls": [], "all_urls": []}, "oa_pdf/85/6f/indmedgaz72181-0032.PMC5231864.pdf": {"url_count": 0, "annot_urls": [], "text_urls": [], "all_urls": []}, "oa_pdf/82/90/indmedgaz72181-0042c.PMC5231865.pdf": {"url_count": 0, "annot_urls": [], "text_urls": [], "all_urls": []}, "oa_pdf/b2/f4/indmedgaz72181-0055c.PMC5231866.pdf": {"url_count": 0, "annot_urls": [], "text_urls": [], "all_urls": []}, "oa_pdf/0b/dd/indmedgaz72181-0023a.PMC5231867.pdf": {"url_count": 0, "annot_urls": [], "text_urls": [], "all_urls": []}, "oa_pdf/17/32/indmedgaz72181-0042a.PMC5231868.pdf": {"url_count": 0, "annot_urls": [], "text_urls": [], "all_urls": []}, "oa_pdf/b9/75/indmedgaz72181-0056d.PMC5231869.pdf": {"url_count": 0, "annot_urls": [], "text_urls": [], "all_urls": []}, "oa_pdf/54/52/indmedgaz72181-0042b.PMC5231870.pdf": {"url_count": 0, "annot_urls": [], "text_urls": [], "all_urls": []}, "oa_pdf/2e/5e/indmedgaz72181-0023b.PMC5231871.pdf": {"url_count": 0, "annot_urls": [], "text_urls": [], "all_urls": []}, "oa_pdf/5e/da/indmedgaz72181-0039.PMC5231872.pdf": {"url_count": 0, "annot_urls": [], "text_urls": [], "all_urls": []}, "oa_pdf/63/53/indmedgaz72181-0056b.PMC5231873.pdf": {"url_count": 0, "annot_urls": [], "text_urls": [], "all_urls": []}, "oa_pdf/6b/03/indmedgaz72181-0059d.PMC5231874.pdf": {"url_count": 0, "annot_urls": [], "text_urls": [], "all_urls": []}, "oa_pdf/cd/5c/indmedgaz72181-0006.PMC5231875.pdf": {"url_count": 0, "annot_urls": [], "text_urls": [], "all_urls": []}, "oa_pdf/8f/a7/indmedgaz72181-0013.PMC5231876.pdf": {"url_count": 0, "annot_urls": [], "text_urls": [], "all_urls": []}, "oa_pdf/fb/7b/indmedgaz72181-0055a.PMC5231877.pdf": {"url_count": 0, "annot_urls": [], "text_urls": [], "all_urls": []}, "oa_pdf/31/e6/indmedgaz72181-0050.PMC5231878.pdf": {"url_count": 0, "annot_urls": [], "text_urls": [], "all_urls": []}, "oa_pdf/ae/d9/indmedgaz72181-0016.PMC5231880.pdf": {"url_count": 0, "annot_urls": [], "text_urls": [], "all_urls": []}, "oa_pdf/f0/97/edinbmedj75040-0011.PMC5329461.pdf": {"url_count": 0, "annot_urls": [], "text_urls": [], "all_urls": []}, "oa_pdf/e1/a6/edinbmedj75040-0058a.PMC5329465.pdf": {"url_count": 0, "annot_urls": [], "text_urls": [], "all_urls": []}, "oa_pdf/6c/fb/edinbmedj75040-0066b.PMC5329466.pdf": {"url_count": 0, "annot_urls": [], "text_urls": [], "all_urls": []}, "oa_pdf/f3/b9/edinbmedj75040-0091.PMC5329468.pdf": {"url_count": 0, "annot_urls": [], "text_urls": [], "all_urls": []}, "oa_pdf/81/01/edinbmedj75040-0065.PMC5329469.pdf": {"url_count": 0, "annot_urls": [], "text_urls": [], "all_urls": []}, "oa_pdf/96/12/edinbmedj75040-0062.PMC5329470.pdf": {"url_count": 0, "annot_urls": [], "text_urls": [], "all_urls": []}, "oa_pdf/fa/84/edinbmedj75040-0066a.PMC5329471.pdf": {"url_count": 0, "annot_urls": [], "text_urls": [], "all_urls": []}, "oa_pdf/28/8e/edinbmedj75040-0032.PMC5329472.pdf": {"url_count": 0, "annot_urls": [], "text_urls": [], "all_urls": []}, "oa_pdf/cb/84/edinbmedj75040-0058b.PMC5329473.pdf": {"url_count": 0, "annot_urls": [], "text_urls": [], "all_urls": []}, "oa_pdf/37/b4/edinbmedj75040-0059.PMC5329474.pdf": {"url_count": 0, "annot_urls": [], "text_urls": [], "all_urls": []}, "oa_pdf/98/5f/edinbmedj75040-0060.PMC5329475.pdf": {"url_count": 0, "annot_urls": [], "text_urls": [], "all_urls": []}, "oa_pdf/58/72/glasgowmedj75736-0055.PMC5967903.pdf": {"url_count": 0, "annot_urls": [], "text_urls": [], "all_urls": []}, "oa_pdf/8d/59/glasgowmedj75736-0038.PMC5967904.pdf": {"url_count": 0, "annot_urls": [], "text_urls": [], "all_urls": []}, "oa_pdf/54/87/glasgowmedj75736-0052b.PMC5967905.pdf": {"url_count": 0, "annot_urls": [], "text_urls": [], "all_urls": []}, "oa_pdf/46/08/glasgowmedj75736-0044.PMC5967906.pdf": {"url_count": 0, "annot_urls": [], "text_urls": [], "all_urls": []}, "oa_pdf/cd/27/glasgowmedj75736-0036.PMC5967907.pdf": {"url_count": 0, "annot_urls": [], "text_urls": [], "all_urls": []}, "oa_pdf/7a/d6/glasgowmedj75736-0047.PMC5967908.pdf": {"url_count": 0, "annot_urls": [], "text_urls": [], "all_urls": []}, "oa_pdf/49/ef/glasgowmedj75736-0052a.PMC5967909.pdf": {"url_count": 0, "annot_urls": [], "text_urls": [], "all_urls": []}, "oa_pdf/fa/67/glasgowmedj75736-0023.PMC5967910.pdf": {"url_count": 0, "annot_urls": [], "text_urls": [], "all_urls": []}, "oa_pdf/52/a2/glasgowmedj75736-0001.PMC5967913.pdf": {"url_count": 0, "annot_urls": [], "text_urls": [], "all_urls": []}, "oa_pdf/7b/31/glasgowmedj75736-0016.PMC5967914.pdf": {"url_count": 0, "annot_urls": [], "text_urls": [], "all_urls": []}}, "num_files": 116}}